mdformat_sentencebreak/__init__.py
mdformat_sentencebreak/plugin.py
mdformat_sentencebreak-0.4.0.dist-info/entry_points.txt
mdformat_sentencebreak-0.4.0.dist-info/LICENSE
mdformat_sentencebreak-0.4.0.dist-info/WHEEL
mdformat_sentencebreak-0.4.0.dist-info/METADATA
mdformat_sentencebreak-0.4.0.dist-info/RECORD
