Metadata-Version: 2.1
Name: mdformat-sentencebreak
Version: 0.4.0
Summary: Adds a really simple and naive sentence breaking scheme to mdformat
Keywords: mdformat,markdown,markdown-it
Author: J. Sebastian Paez
Author-email: jspaezp@users.noreply.github.com
Requires-Python: >=3.8,<4.0
Classifier: Intended Audience :: Developers
Classifier: License :: OSI Approved :: MIT License
Classifier: Programming Language :: Python :: 3
Classifier: Programming Language :: Python :: 3.8
Classifier: Programming Language :: Python :: 3.9
Classifier: Programming Language :: Python :: 3.10
Classifier: Programming Language :: Python :: 3
Classifier: Topic :: Software Development :: Libraries :: Python Modules
Requires-Dist: mdformat (>=0.7.16,<0.8.0)
